summarizers/__init__.py
summarizers/summarizers.py
summarizers-1.0.4.dist-info/LICENSE
summarizers-1.0.4.dist-info/METADATA
summarizers-1.0.4.dist-info/WHEEL
summarizers-1.0.4.dist-info/top_level.txt
summarizers-1.0.4.dist-info/RECORD
