Metadata-Version: 2.1
Name: summarizers
Version: 1.0.4
Summary: opensource text summarization toolkit.
Home-page: https://github.com/hyunwoongko/summarizers
Author: Hyunwoong Ko
Author-email: gusdnd852@naver.com
License: UNKNOWN
Platform: UNKNOWN
Classifier: Programming Language :: Python :: 3
Classifier: Programming Language :: Python :: 3.2
Classifier: Programming Language :: Python :: 3.3
Classifier: Programming Language :: Python :: 3.4
Classifier: Programming Language :: Python :: 3.5
Classifier: Programming Language :: Python :: 3.6
Classifier: Programming Language :: Python :: 3.7
Classifier: Programming Language :: Python :: 3.8
Classifier: Programming Language :: Python :: 3.9
Classifier: Topic :: Scientific/Engineering :: Artificial Intelligence
Classifier: Topic :: Software Development :: Libraries
Requires-Python: >=3
Requires-Dist: transformers (>=4)
Requires-Dist: torch
